odoo/addons/sale_order_restrict_copy_archived_product/README.rst
odoo/addons/sale_order_restrict_copy_archived_product/__init__.py
odoo/addons/sale_order_restrict_copy_archived_product/__manifest__.py
odoo/addons/sale_order_restrict_copy_archived_product/i18n/es.po
odoo/addons/sale_order_restrict_copy_archived_product/i18n/sale_order_restrict_copy_archived_product.pot
odoo/addons/sale_order_restrict_copy_archived_product/models/__init__.py
odoo/addons/sale_order_restrict_copy_archived_product/models/sale_order.py
odoo/addons/sale_order_restrict_copy_archived_product/readme/CONTRIBUTORS.md
odoo/addons/sale_order_restrict_copy_archived_product/readme/DESCRIPTION.md
odoo/addons/sale_order_restrict_copy_archived_product/readme/USAGE.md
odoo/addons/sale_order_restrict_copy_archived_product/static/description/icon.png
odoo/addons/sale_order_restrict_copy_archived_product/static/description/icon.svg
odoo/addons/sale_order_restrict_copy_archived_product/static/description/index.html
odoo/addons/sale_order_restrict_copy_archived_product/tests/__init__.py
odoo/addons/sale_order_restrict_copy_archived_product/tests/test_sale_order_restrict_copy_archived_product.py
odoo_addon_sale_order_restrict_copy_archived_product-15.0.1.0.0.4.dist-info/METADATA
odoo_addon_sale_order_restrict_copy_archived_product-15.0.1.0.0.4.dist-info/WHEEL
odoo_addon_sale_order_restrict_copy_archived_product-15.0.1.0.0.4.dist-info/top_level.txt
odoo_addon_sale_order_restrict_copy_archived_product-15.0.1.0.0.4.dist-info/RECORD
